README.md
setup.py
cameo_geo_query/__init__.py
cameo_geo_query/cameo_geo_query.py
cameo_geo_query.egg-info/PKG-INFO
cameo_geo_query.egg-info/SOURCES.txt
cameo_geo_query.egg-info/dependency_links.txt
cameo_geo_query.egg-info/requires.txt
cameo_geo_query.egg-info/top_level.txt