Metadata-Version: 2.1
Name: cameo_geo_query
Version: 1.0.35
Summary: This is cameo_geo_query
Home-page: 
Author: bear
Author-email: panda19931217@gmail.com
License: BSD 2-clause
Requires-Dist: pandas
Requires-Dist: geopy
Requires-Dist: plotly
Requires-Dist: cameo-botrun-prompt-tools>=1.0.6
Requires-Dist: python-dotenv
